streaq/__init__.py
streaq/__main__.py
streaq/cli.py
streaq/constants.py
streaq/py.typed
streaq/task.py
streaq/types.py
streaq/utils.py
streaq/worker.py
streaq/lua/streaq.lua
streaq/ui/__init__.py
streaq/ui/deps.py
streaq/ui/tasks.py
streaq/ui/templates/base.j2
streaq/ui/templates/queue.j2
streaq/ui/templates/table.j2
streaq/ui/templates/task.j2
streaq-6.0.0.dist-info/METADATA
streaq-6.0.0.dist-info/WHEEL
streaq-6.0.0.dist-info/entry_points.txt
streaq-6.0.0.dist-info/licenses/LICENSE
streaq-6.0.0.dist-info/RECORD
