Metadata-Version: 2.4
Name: streaq
Version: 6.0.0
Summary: Fast, async, fully-typed distributed task queue via Redis streams
Project-URL: Homepage, https://github.com/tastyware/streaq
Project-URL: Documentation, https://streaq.rtfd.io
Project-URL: Funding, https://github.com/sponsors/tastyware
Project-URL: Source, https://github.com/tastyware/streaq
Project-URL: Changelog, https://github.com/tastyware/streaq/releases
Author-email: Graeme Holliday <graeme@tastyware.dev>
License: MIT License
License-File: LICENSE
Classifier: Development Status :: 5 - Production/Stable
Classifier: Environment :: Console
Classifier: Framework :: AnyIO
Classifier: Framework :: AsyncIO
Classifier: Framework :: Django
Classifier: Framework :: FastAPI
Classifier: Framework :: Flask
Classifier: Framework :: Trio
Classifier: Intended Audience :: Developers
Classifier: Intended Audience :: Information Technology
Classifier: Intended Audience :: System Administrators
Classifier: License :: OSI Approved :: MIT License
Classifier: Operating System :: MacOS :: MacOS X
Classifier: Operating System :: Microsoft :: Windows
Classifier: Operating System :: POSIX :: Linux
Classifier: Operating System :: Unix
Classifier: Programming Language :: Python
Classifier: Programming Language :: Python :: 3
Classifier: Programming Language :: Python :: 3 :: Only
Classifier: Programming Language :: Python :: 3.10
Classifier: Programming Language :: Python :: 3.11
Classifier: Programming Language :: Python :: 3.12
Classifier: Programming Language :: Python :: 3.13
Classifier: Programming Language :: Python :: 3.14
Classifier: Topic :: Software Development :: Libraries :: Python Modules
Classifier: Topic :: System :: Clustering
Classifier: Topic :: System :: Distributed Computing
Classifier: Topic :: System :: Monitoring
Classifier: Topic :: System :: Systems Administration
Classifier: Typing :: Typed
Requires-Python: >=3.10
Requires-Dist: anyio>=4.11.0
Requires-Dist: coredis
Requires-Dist: crontab>=1.0.5
Requires-Dist: typer>=0.19.2
Requires-Dist: uvloop>=0.21.0; sys_platform != 'win32'
Requires-Dist: watchfiles>=1.1.0
Provides-Extra: benchmark
Requires-Dist: arq==0.26.3; extra == 'benchmark'
Requires-Dist: saq[hiredis]==0.25.2; extra == 'benchmark'
Requires-Dist: taskiq-redis==1.1.0; extra == 'benchmark'
Provides-Extra: web
Requires-Dist: async-lru>=2.0.5; extra == 'web'
Requires-Dist: fastapi>=0.117.1; extra == 'web'
Requires-Dist: jinja2>=3.1.6; extra == 'web'
Requires-Dist: python-multipart>=0.0.20; extra == 'web'
Requires-Dist: uvicorn>=0.37.0; extra == 'web'
